prelims/__init__.py
prelims/handler.py
prelims/post.py
prelims/processor/__init__.py
prelims/processor/base.py
prelims/processor/lastmod.py
prelims/processor/opengraph.py
prelims/processor/recommender.py
prelims-0.0.7.dist-info/LICENSE
prelims-0.0.7.dist-info/METADATA
prelims-0.0.7.dist-info/WHEEL
prelims-0.0.7.dist-info/top_level.txt
prelims-0.0.7.dist-info/RECORD
