Metadata-Version: 2.1
Name: prelims
Version: 0.0.7
Summary: Front matter post-processor for static site generators
Home-page: https://github.com/takuti/prelims
Download-URL: https://pypi.org/project/prelims/#files
Author: Takuya Kitazawa
Author-email: k.takuti@gmail.com
License: MIT
Classifier: Intended Audience :: Developers
Classifier: License :: OSI Approved
Classifier: Programming Language :: Python
Classifier: Topic :: Internet :: WWW/HTTP :: Dynamic Content :: News/Diary
Classifier: Topic :: Office/Business :: News/Diary
Classifier: Topic :: Software Development
Classifier: Topic :: Text Processing :: Markup
Classifier: Development Status :: 3 - Alpha
Classifier: Operating System :: Microsoft :: Windows
Classifier: Operating System :: POSIX
Classifier: Operating System :: Unix
Classifier: Operating System :: MacOS
Classifier: Programming Language :: Python :: 3
Classifier: Programming Language :: Python :: 3.7
Classifier: Programming Language :: Python :: 3.8
Classifier: Programming Language :: Python :: 3.9
Requires-Python: >=3.7
License-File: LICENSE
Requires-Dist: numpy (>=1.14.6)
Requires-Dist: scikit-learn (>=1.0)
Requires-Dist: PyYAML (>=5.1)
